setup.py
mini_stata/__init__.py
mini_stata/data_description.py
mini_stata.egg-info/PKG-INFO
mini_stata.egg-info/SOURCES.txt
mini_stata.egg-info/dependency_links.txt
mini_stata.egg-info/not-zip-safe
mini_stata.egg-info/top_level.txt