Metadata-Version: 1.0
Name: mini-stata
Version: 0.1
Summary: The mini version of stata
Home-page: https://github.com/quyennguyen2201
Author: Quyen Nguyen
Author-email: quyen.nguyen@postgrad.otago.ac.nz
License: MIT
Platform: UNKNOWN
